setup.py
pyico/__init__.py
pyico/binary.py
pyico/bmp.py
pyico/info.py
pyico.egg-info/PKG-INFO
pyico.egg-info/SOURCES.txt
pyico.egg-info/dependency_links.txt
pyico.egg-info/top_level.txt
pyico.egg-info/zip-safe