Metadata-Version: 1.0
Name: pyico
Version: 0.1.52
Summary: pyico v. 0.1.51
